CHANGELOG.md
LICENSE.txt
MANIFEST.in
README.md
pytest_session_fixture_globalize.py
setup.py
pytest_session_fixture_globalize.egg-info/PKG-INFO
pytest_session_fixture_globalize.egg-info/SOURCES.txt
pytest_session_fixture_globalize.egg-info/dependency_links.txt
pytest_session_fixture_globalize.egg-info/entry_points.txt
pytest_session_fixture_globalize.egg-info/not-zip-safe
pytest_session_fixture_globalize.egg-info/requires.txt
pytest_session_fixture_globalize.egg-info/top_level.txt